tests/__init__.py
tests/test.py
tests/tokenizers.py
textrankr/__init__.py
textrankr/sentence.py
textrankr/textrank.py
textrankr/utils.py
textrankr-1.1.dist-info/LICENSE
textrankr-1.1.dist-info/METADATA
textrankr-1.1.dist-info/WHEEL
textrankr-1.1.dist-info/top_level.txt
textrankr-1.1.dist-info/RECORD
