Metadata-Version: 2.1
Name: textrankr
Version: 1.1
Summary: TextRank implemented in Python.
Home-page: https://github.com/theeluwin/textrankr
Author: Jamie Seol
Author-email: theeluwin@gmail.com
License: MIT
Platform: UNKNOWN
Requires-Dist: setuptools
Requires-Dist: networkx
